cfg1/__init__.py
cfg1/loader.py
cfg1-0.0.3.dist-info/WHEEL
cfg1-0.0.3.dist-info/METADATA
cfg1-0.0.3.dist-info/RECORD
