Metadata-Version: 2.1
Name: cfg1
Version: 0.0.3
Summary: A configuration library for Python3 projects
Author: Dan Sikes
Author-email: dansikes7@gmail.com
Requires-Python: >=3.0.0,<4.0.0
Classifier: Programming Language :: Python :: 3
Classifier: Programming Language :: Python :: 3.10
Classifier: Programming Language :: Python :: 3.4
Classifier: Programming Language :: Python :: 3.5
Classifier: Programming Language :: Python :: 3.6
Classifier: Programming Language :: Python :: 3.7
Classifier: Programming Language :: Python :: 3.8
Classifier: Programming Language :: Python :: 3.9
Requires-Dist: pyaml (>=21.10.1,<22.0.0)
Requires-Dist: pytest (>=7.1.2,<8.0.0)
Requires-Dist: python-box (>=6.0.2,<7.0.0)
